xingchen/__init__.py
xingchen/aca_util.py
xingchen/api_client.py
xingchen/api_response.py
xingchen/configuration.py
xingchen/exceptions.py
xingchen/py.typed
xingchen/rest.py
xingchen/api/__init__.py
xingchen/api/character_api_sub.py
xingchen/api/chat_api_sub.py
xingchen/api/chat_extract_message_api_sub.py
xingchen/api/chat_message_api_sub.py
xingchen/api/common_api_sub.py
xingchen/api/completion_api_sub.py
xingchen/api/groupchat_api_sub.py
xingchen/api/knowledge_base_api_sub.py
xingchen/models/__init__.py
xingchen/models/advanced_settings.py
xingchen/models/base_chat_request.py
xingchen/models/base_chat_request_aca_chat_ext_param.py
xingchen/models/character_advanced_config.py
xingchen/models/character_create_dto.py
xingchen/models/character_desc_dto.py
xingchen/models/character_desc_generated_request.py
xingchen/models/character_dto.py
xingchen/models/character_key.py
xingchen/models/character_permission_config.py
xingchen/models/character_query_dto.py
xingchen/models/character_query_where.py
xingchen/models/character_update_dto.py
xingchen/models/character_version_create_or_update_dto.py
xingchen/models/chat_context.py
xingchen/models/chat_history_query_dto.py
xingchen/models/chat_history_query_where.py
xingchen/models/chat_message_dto.py
xingchen/models/chat_req_params.py
xingchen/models/chat_room_user_dto.py
xingchen/models/context.py
xingchen/models/extract_data.py
xingchen/models/extract_kv_dto.py
xingchen/models/extract_memory_request.py
xingchen/models/extract_summary_dto.py
xingchen/models/file_conver_dto.py
xingchen/models/file_conver_request.py
xingchen/models/file_info_vo.py
xingchen/models/function_call.py
xingchen/models/gateway_context.py
xingchen/models/gateway_issued_params.py
xingchen/models/input.py
xingchen/models/keyword.py
xingchen/models/knowledge_base_create_dto.py
xingchen/models/knowledge_base_delete_dto.py
xingchen/models/knowledge_base_detail_delete_dto.py
xingchen/models/knowledge_base_detail_dto.py
xingchen-1.1.5.dist-info/METADATA
xingchen-1.1.5.dist-info/WHEEL
xingchen-1.1.5.dist-info/top_level.txt
xingchen-1.1.5.dist-info/RECORD
